{
  "mainLinks": [
    {
      "name": "Stay",
      "url": "/stay",
      "title": "Stay"
    },
    {
      "name": "Fine Dine",
      "url": "/dine",
      "title": "Dine"
    },
    {
      "name": "Recreation",
      "url": "/recreation",
      "title": "Recreation"
    },
    {
      "name": "Events",
      "url": "/events",
      "title": "Events"
    }
  ],
  "secondaryLinks": [
    {
      "name": "About the Hotel",
      "url": "/about",
      "title": "About"
    },
    {
      "name": "Gallery",
      "url": "/gallery",
      "title": "Gallery"
    },
    {
      "name": "Nearby Places",
      "url": "/places",
      "title": "Nearby Places"
    },
    {
      "name": "Download Brochure",
      "url": "/brochure",
      "title": "Download Brochure"
    },
    {
      "name": "Contact Us",
      "url": "/contact",
      "title": "Contact"
    },
    {
      "name": "Inquiry",
      "url": "/inquiry",
      "title": "Inquiry"
    },
    {
      "name": "Promotions",
      "url": "/promotions",
      "title": "Promotions"
    },
    {
      "name": "Social Media Posts",
      "url": "/social-offer",
      "title": "Social Media Posts"
    }
  ],
  "bookingInfo": {
    "roomBooking": {
      "title": "Room Booking",
      "phone": "+977-9851139592",
      "email": "reservation@hotelhimalaya.com"
    },
    "eventBooking": {
      "title": "Event Booking",
      "phones": [
        "+977 9761693040",
        "+977 9801810708"
      ],
      "email": "banquetsales@hotelhimalaya.com"
    },
    "dineRecreationBooking": {
      "title": "Dine & Recreation Booking",
      "phones": [
        "+977-9851339602",
        "+977-9801810708"
      ],
      "email": "info@hotelhimalaya.com"
    },
    "patanMuseumCafeBooking": {
      "title": "Patan Museum Cafe Booking",
      "phone": "+977-9851339602",
      "email": "pmc@hotelhimalaya.com"
    }
  },
  "hospitalityPartners": [
    {
      "name": "Miss World",
      "logo": "../images/hospitality/missWorld.png"
    },
    {
      "name": "Miss Earth",
      "logo": "../images/hospitality/missEarth.png"
    },
    {
      "name": "Miss International",
      "logo": "../images/hospitality/missInternational.png"
    }
  ],
  "copyright": {
    "year": "2024",
    "owner": "Hotel Himalaya",
    "developer": "Purna Shrestha",
    "developerLink": "https://www.purnashrestha.com.np/"
  }
}